keras_tpu/__init__.py
keras_tpu-0.0.2.dist-info/METADATA
keras_tpu-0.0.2.dist-info/RECORD
keras_tpu-0.0.2.dist-info/WHEEL
keras_tpu-0.0.2.dist-info/top_level.txt
